copied_document_checker/__init__.py
copied_document_checker/copied_doc_checker.py
"copied_document_checker/students_homeworks_example/20120535_2019-04-03_17,30,06-(0).pdf"
"copied_document_checker/students_homeworks_example/20130523_2019-04-02_21,27,08-(0).pdf"
"copied_document_checker/students_homeworks_example/20130562_2019-04-03_17,28,52-(0).pdf"
"copied_document_checker/students_homeworks_example/20140538_2019-04-02_09,06,26-(0).docx"
"copied_document_checker/students_homeworks_example/20140539_2019-04-01_20,47,04-(0).docx"
"copied_document_checker/students_homeworks_example/20140542_2019-04-03_14,27,19-(0).pdf"
"copied_document_checker/students_homeworks_example/20140543_2019-04-03_14,39,37-(0).pdf"
"copied_document_checker/students_homeworks_example/20140550_2019-04-03_12,19,12-(0).pdf"
"copied_document_checker/students_homeworks_example/20140556_2019-04-01_09,43,59-(0).pdf"
"copied_document_checker/students_homeworks_example/20140558_2019-04-03_14,08,54-(0).pdf"
"copied_document_checker/students_homeworks_example/20140564_2019-04-03_12,45,06-(0).pdf"
"copied_document_checker/students_homeworks_example/20140568_2019-04-01_15,47,41-(0).docx"
"copied_document_checker/students_homeworks_example/20140569_2019-04-03_12,47,14-(0).pdf"
"copied_document_checker/students_homeworks_example/20140571_2019-04-03_14,32,53-(0).pdf"
"copied_document_checker/students_homeworks_example/20140572_2019-04-01_21,05,50-(0).docx"
"copied_document_checker/students_homeworks_example/20140580_2019-04-03_11,05,00-(0).pdf"
"copied_document_checker/students_homeworks_example/20141527_2019-04-03_17,04,54-(0).pdf"
"copied_document_checker/students_homeworks_example/20150668_2019-04-03_17,24,27-(0).pdf"
"copied_document_checker/students_homeworks_example/20160653_2019-04-03_12,58,48-(0).pdf"
"copied_document_checker/students_homeworks_example/20160671_2019-04-03_12,03,50-(0).pdf"
"copied_document_checker/students_homeworks_example/20160681_2019-04-03_12,52,17-(0).pdf"
copied_document_checker-1.4.dist-info/METADATA
copied_document_checker-1.4.dist-info/RECORD
copied_document_checker-1.4.dist-info/WHEEL
copied_document_checker-1.4.dist-info/top_level.txt
