Metadata-Version: 2.1
Name: copied-document-checker
Version: 1.4
Summary: Find out matched documents that are likely to be copied.
Home-page: https://github.com/danelee2601/copied_document_checker
Author: Daesoo Lee
Author-email: danelee2601@naver.com
License: UNKNOWN
Keywords: copied documents,plagiarism,plagiarize
Platform: UNKNOWN
Requires-Python: >=3
